{
  "pdf_page": 56,
  "printed_label": "Rohit Khanna 56 of 210",
  "section": "Schedule A: Assets and Unearned Income",
  "page_type": "schedule_a",
  "filer": "Rohit Khanna",
  "layout_note": "Continuation of the block-split transposed Schedule A sheet under trust header 'Mita Ahuja 1994 Trust' (same layout as page 55). Columns present: owner (SP/DC/JT) + Asset Name, EIF, a wide 'Amount of Income' value-matrix, and a 'Transaction Summary' block (three columns read as P / S / E). No Value (Block B) or Type-of-Income (Block C) grids. Owner reads SP for every row. As on page 55, the Amount-of-Income and Transaction-Summary X-marks are visible but the ~12 amount columns are too narrowly spaced at native resolution to assign to a single bucket without off-by-one error, so those grids are left null (no silent guessing). This page's scan is more degraded than page 55; several asset names are best-effort identifications from alphabetical position and are flagged in uncertainties. asset_name and owner are the transcribed data.",
  "rows": [
    {"kind": "asset", "owner": "SP", "asset_name": "CONSTELLATION BRANDS INC CMN CLASS A", "eif": null, "value": null, "income_types": null, "other_income_spec": null, "amount_of_income": null, "transaction": null},
    {"kind": "asset", "owner": "SP", "asset_name": "CONTINENTAL RESOURCES, INC CMN", "eif": null, "value": null, "income_types": null, "other_income_spec": null, "amount_of_income": null, "transaction": null},
    {"kind": "asset", "owner": "SP", "asset_name": "COOPER COMPANIES INC (THE) CMN", "eif": null, "value": null, "income_types": null, "other_income_spec": null, "amount_of_income": null, "transaction": null},
    {"kind": "asset", "owner": "SP", "asset_name": "COPART INC CMN", "eif": null, "value": null, "income_types": null, "other_income_spec": null, "amount_of_income": null, "transaction": null},
    {"kind": "asset", "owner": "SP", "asset_name": "CORNING INCORPORATED CMN", "eif": null, "value": null, "income_types": null, "other_income_spec": null, "amount_of_income": null, "transaction": null},
    {"kind": "asset", "owner": "SP", "asset_name": "CORTEVA, INC. CMN", "eif": null, "value": null, "income_types": null, "other_income_spec": null, "amount_of_income": null, "transaction": null},
    {"kind": "asset", "owner": "SP", "asset_name": "COSTCO WHOLESALE CORPORATION CMN", "eif": null, "value": null, "income_types": null, "other_income_spec": null, "amount_of_income": null, "transaction": null},
    {"kind": "asset", "owner": "SP", "asset_name": "COTY, INC. CMN CLASS A", "eif": null, "value": null, "income_types": null, "other_income_spec": null, "amount_of_income": null, "transaction": null},
    {"kind": "asset", "owner": "SP", "asset_name": "CAMPBELL CNTY KY SCH DIST FIN CORP REV 5.xxx% 12/01/24 IO BDS CAMPBELL CY M&M REMK PRERE 12/01/19 O/O", "eif": null, "value": null, "income_types": null, "other_income_spec": null, "amount_of_income": null, "transaction": null},
    {"kind": "asset", "owner": "SP", "asset_name": "CROWN CASTLE INTL CORP CMN", "eif": null, "value": null, "income_types": null, "other_income_spec": null, "amount_of_income": null, "transaction": null},
    {"kind": "asset", "owner": "SP", "asset_name": "CSX CORPORATION CMN", "eif": null, "value": null, "income_types": null, "other_income_spec": null, "amount_of_income": null, "transaction": null},
    {"kind": "asset", "owner": "SP", "asset_name": "CUMMINS INC COMMON STOCK", "eif": null, "value": null, "income_types": null, "other_income_spec": null, "amount_of_income": null, "transaction": null},
    {"kind": "asset", "owner": "SP", "asset_name": "CVS HEALTH CORP CMN", "eif": null, "value": null, "income_types": null, "other_income_spec": null, "amount_of_income": null, "transaction": null},
    {"kind": "asset", "owner": "SP", "asset_name": "CYPRESS SEMICONDUCTOR CORP CMN", "eif": null, "value": null, "income_types": null, "other_income_spec": null, "amount_of_income": null, "transaction": null},
    {"kind": "asset", "owner": "SP", "asset_name": "D.R. HORTON, INC. CMN", "eif": null, "value": null, "income_types": null, "other_income_spec": null, "amount_of_income": null, "transaction": null},
    {"kind": "asset", "owner": "SP", "asset_name": "DANAHER CORPORATION CMN", "eif": null, "value": null, "income_types": null, "other_income_spec": null, "amount_of_income": null, "transaction": null},
    {"kind": "asset", "owner": "SP", "asset_name": "DARDEN RESTAURANTS, INC. CMN", "eif": null, "value": null, "income_types": null, "other_income_spec": null, "amount_of_income": null, "transaction": null},
    {"kind": "asset", "owner": "SP", "asset_name": "DAVITA INC CMN", "eif": null, "value": null, "income_types": null, "other_income_spec": null, "amount_of_income": null, "transaction": null},
    {"kind": "asset", "owner": "SP", "asset_name": "DEERE & COMPANY CMN", "eif": null, "value": null, "income_types": null, "other_income_spec": null, "amount_of_income": null, "transaction": null},
    {"kind": "asset", "owner": "SP", "asset_name": "DELL TECHNOLOGIES INC. CMN", "eif": null, "value": null, "income_types": null, "other_income_spec": null, "amount_of_income": null, "transaction": null},
    {"kind": "asset", "owner": "SP", "asset_name": "DELTA AIR LINES, INC. CMN", "eif": null, "value": null, "income_types": null, "other_income_spec": null, "amount_of_income": null, "transaction": null},
    {"kind": "asset", "owner": "SP", "asset_name": "DENTSPLY SIRONA INC CMN", "eif": null, "value": null, "income_types": null, "other_income_spec": null, "amount_of_income": null, "transaction": null},
    {"kind": "asset", "owner": "SP", "asset_name": "DEVON ENERGY CORPORATION (DVN) CMN", "eif": null, "value": null, "income_types": null, "other_income_spec": null, "amount_of_income": null, "transaction": null},
    {"kind": "asset", "owner": "SP", "asset_name": "DIAMONDBACK ENERGY INC CMN", "eif": null, "value": null, "income_types": null, "other_income_spec": null, "amount_of_income": null, "transaction": null},
    {"kind": "asset", "owner": "SP", "asset_name": "DICKS SPORTING GOODS INC CMN", "eif": null, "value": null, "income_types": null, "other_income_spec": null, "amount_of_income": null, "transaction": null},
    {"kind": "asset", "owner": "SP", "asset_name": "DIGITAL REALTY TRUST, INC. CMN", "eif": null, "value": null, "income_types": null, "other_income_spec": null, "amount_of_income": null, "transaction": null},
    {"kind": "asset", "owner": "SP", "asset_name": "DISCOVER FINANCIAL SERVICES CMN", "eif": null, "value": null, "income_types": null, "other_income_spec": null, "amount_of_income": null, "transaction": null},
    {"kind": "asset", "owner": "SP", "asset_name": "DISCOVERY INC - A CMN SERIES A", "eif": null, "value": null, "income_types": null, "other_income_spec": null, "amount_of_income": null, "transaction": null},
    {"kind": "asset", "owner": "SP", "asset_name": "DISCOVERY INC CMN", "eif": null, "value": null, "income_types": null, "other_income_spec": null, "amount_of_income": null, "transaction": null},
    {"kind": "asset", "owner": "SP", "asset_name": "DISH NETWORK CORPORATION CMN CLASS A", "eif": null, "value": null, "income_types": null, "other_income_spec": null, "amount_of_income": null, "transaction": null},
    {"kind": "asset", "owner": "SP", "asset_name": "DOLLAR GENERAL CORPORATION CMN", "eif": null, "value": null, "income_types": null, "other_income_spec": null, "amount_of_income": null, "transaction": null},
    {"kind": "asset", "owner": "SP", "asset_name": "DOLLAR TREE STORES, INC. CMN", "eif": null, "value": null, "income_types": null, "other_income_spec": null, "amount_of_income": null, "transaction": null},
    {"kind": "asset", "owner": "SP", "asset_name": "DOMINION ENERGY INC CMN", "eif": null, "value": null, "income_types": null, "other_income_spec": null, "amount_of_income": null, "transaction": null},
    {"kind": "asset", "owner": "SP", "asset_name": "DOMTAR CORPORATION CMN", "eif": null, "value": null, "income_types": null, "other_income_spec": null, "amount_of_income": null, "transaction": null},
    {"kind": "asset", "owner": "SP", "asset_name": "DOVER CORPORATION CMN", "eif": null, "value": null, "income_types": null, "other_income_spec": null, "amount_of_income": null, "transaction": null},
    {"kind": "asset", "owner": "SP", "asset_name": "DOW INC. CMN", "eif": null, "value": null, "income_types": null, "other_income_spec": null, "amount_of_income": null, "transaction": null},
    {"kind": "asset", "owner": "SP", "asset_name": "DROPBOX, INC. CMN CLASS A", "eif": null, "value": null, "income_types": null, "other_income_spec": null, "amount_of_income": null, "transaction": null},
    {"kind": "asset", "owner": "SP", "asset_name": "DTE ENERGY COMPANY CMN", "eif": null, "value": null, "income_types": null, "other_income_spec": null, "amount_of_income": null, "transaction": null},
    {"kind": "asset", "owner": "SP", "asset_name": "DUKE ENERGY CORPORATION CMN", "eif": null, "value": null, "income_types": null, "other_income_spec": null, "amount_of_income": null, "transaction": null},
    {"kind": "asset", "owner": "SP", "asset_name": "DUKE REALTY CORPORATION CMN", "eif": null, "value": null, "income_types": null, "other_income_spec": null, "amount_of_income": null, "transaction": null},
    {"kind": "asset", "owner": "SP", "asset_name": "DUPONT DE NEMOURS INC CMN", "eif": null, "value": null, "income_types": null, "other_income_spec": null, "amount_of_income": null, "transaction": null},
    {"kind": "asset", "owner": "SP", "asset_name": "DUPONT DE NEMOURS, INC. CMN", "eif": null, "value": null, "income_types": null, "other_income_spec": null, "amount_of_income": null, "transaction": null},
    {"kind": "asset", "owner": "SP", "asset_name": "DXC TECHNOLOGY COMPANY CMN", "eif": null, "value": null, "income_types": null, "other_income_spec": null, "amount_of_income": null, "transaction": null},
    {"kind": "asset", "owner": "SP", "asset_name": "E*TRADE FINANCIAL CORPORATION CMN", "eif": null, "value": null, "income_types": null, "other_income_spec": null, "amount_of_income": null, "transaction": null},
    {"kind": "asset", "owner": "SP", "asset_name": "EAST WEST BANCORP INC CMN", "eif": null, "value": null, "income_types": null, "other_income_spec": null, "amount_of_income": null, "transaction": null},
    {"kind": "asset", "owner": "SP", "asset_name": "EASTMAN CHEMICAL COMPANY CMN", "eif": null, "value": null, "income_types": null, "other_income_spec": null, "amount_of_income": null, "transaction": null},
    {"kind": "asset", "owner": "SP", "asset_name": "EATON CORP PLC CMN", "eif": null, "value": null, "income_types": null, "other_income_spec": null, "amount_of_income": null, "transaction": null},
    {"kind": "asset", "owner": "SP", "asset_name": "EATON VANCE CORP (NON-VTG) CMN", "eif": null, "value": null, "income_types": null, "other_income_spec": null, "amount_of_income": null, "transaction": null},
    {"kind": "asset", "owner": "SP", "asset_name": "EBAY INC. CMN", "eif": null, "value": null, "income_types": null, "other_income_spec": null, "amount_of_income": null, "transaction": null},
    {"kind": "asset", "owner": "SP", "asset_name": "ECOLAB INC. CMN", "eif": null, "value": null, "income_types": null, "other_income_spec": null, "amount_of_income": null, "transaction": null},
    {"kind": "asset", "owner": "SP", "asset_name": "EDISON INTERNATIONAL CMN", "eif": null, "value": null, "income_types": null, "other_income_spec": null, "amount_of_income": null, "transaction": null},
    {"kind": "asset", "owner": "SP", "asset_name": "EDWARDS LIFESCIENCES CORPORATI CMN", "eif": null, "value": null, "income_types": null, "other_income_spec": null, "amount_of_income": null, "transaction": null},
    {"kind": "asset", "owner": "SP", "asset_name": "ELANCO ANIMAL HEALTH INCORPORA CMN", "eif": null, "value": null, "income_types": null, "other_income_spec": null, "amount_of_income": null, "transaction": null},
    {"kind": "asset", "owner": "SP", "asset_name": "ELECTRONIC ARTS CMN", "eif": null, "value": null, "income_types": null, "other_income_spec": null, "amount_of_income": null, "transaction": null},
    {"kind": "asset", "owner": "SP", "asset_name": "ELI LILLY & CO CMN", "eif": null, "value": null, "income_types": null, "other_income_spec": null, "amount_of_income": null, "transaction": null},
    {"kind": "asset", "owner": "SP", "asset_name": "EMERSON ELECTRIC CO. CMN", "eif": null, "value": null, "income_types": null, "other_income_spec": null, "amount_of_income": null, "transaction": null},
    {"kind": "asset", "owner": "SP", "asset_name": "ENCOMPASS HEALTH CORPORATION CMN", "eif": null, "value": null, "income_types": null, "other_income_spec": null, "amount_of_income": null, "transaction": null},
    {"kind": "asset", "owner": "SP", "asset_name": "ENERGIZER HOLDINGS, INC. CMN", "eif": null, "value": null, "income_types": null, "other_income_spec": null, "amount_of_income": null, "transaction": null},
    {"kind": "asset", "owner": "SP", "asset_name": "ENTEGRIS, INC. CMN", "eif": null, "value": null, "income_types": null, "other_income_spec": null, "amount_of_income": null, "transaction": null},
    {"kind": "asset", "owner": "SP", "asset_name": "ENTERGY CORPORATION CMN", "eif": null, "value": null, "income_types": null, "other_income_spec": null, "amount_of_income": null, "transaction": null},
    {"kind": "asset", "owner": "SP", "asset_name": "EOG RESOURCES INC CMN", "eif": null, "value": null, "income_types": null, "other_income_spec": null, "amount_of_income": null, "transaction": null},
    {"kind": "asset", "owner": "SP", "asset_name": "EPHRATA PA AREA SCH DIST GO 4% 09/01/19 MS SD SCH 2016 UT INS QUAL BEO", "eif": null, "value": null, "income_types": null, "other_income_spec": null, "amount_of_income": null, "transaction": null},
    {"kind": "asset", "owner": "SP", "asset_name": "EQT CORPORATION CMN", "eif": null, "value": null, "income_types": null, "other_income_spec": null, "amount_of_income": null, "transaction": null},
    {"kind": "asset", "owner": "SP", "asset_name": "EQUIFAX INC. CMN", "eif": null, "value": null, "income_types": null, "other_income_spec": null, "amount_of_income": null, "transaction": null},
    {"kind": "asset", "owner": "SP", "asset_name": "EQUINIX, INC. REIT", "eif": null, "value": null, "income_types": null, "other_income_spec": null, "amount_of_income": null, "transaction": null},
    {"kind": "asset", "owner": "SP", "asset_name": "EQUITY RESIDENTIAL CMN", "eif": null, "value": null, "income_types": null, "other_income_spec": null, "amount_of_income": null, "transaction": null},
    {"kind": "asset", "owner": "SP", "asset_name": "ESSEX PROPERTY TRUST INC CMN", "eif": null, "value": null, "income_types": null, "other_income_spec": null, "amount_of_income": null, "transaction": null},
    {"kind": "asset", "owner": "SP", "asset_name": "ESTEE LAUDER COS INC CL-A CMN CLASS A", "eif": null, "value": null, "income_types": null, "other_income_spec": null, "amount_of_income": null, "transaction": null},
    {"kind": "asset", "owner": "SP", "asset_name": "ETSY, INC. CMN", "eif": null, "value": null, "income_types": null, "other_income_spec": null, "amount_of_income": null, "transaction": null},
    {"kind": "asset", "owner": "SP", "asset_name": "EVERGY, INC. CMN", "eif": null, "value": null, "income_types": null, "other_income_spec": null, "amount_of_income": null, "transaction": null},
    {"kind": "asset", "owner": "SP", "asset_name": "EXACT SCIENCES CORPORATION CMN", "eif": null, "value": null, "income_types": null, "other_income_spec": null, "amount_of_income": null, "transaction": null},
    {"kind": "asset", "owner": "SP", "asset_name": "EXELIXIS, INC. CMN", "eif": null, "value": null, "income_types": null, "other_income_spec": null, "amount_of_income": null, "transaction": null},
    {"kind": "asset", "owner": "SP", "asset_name": "EXELON CORPORATION CMN", "eif": null, "value": null, "income_types": null, "other_income_spec": null, "amount_of_income": null, "transaction": null},
    {"kind": "asset", "owner": "SP", "asset_name": "EXETER TWP PA SCH DIST GO 4% 08/04/19 MS GO BDS 2017 LT INS QUAL BEO", "eif": null, "value": null, "income_types": null, "other_income_spec": null, "amount_of_income": null, "transaction": null},
    {"kind": "asset", "owner": "SP", "asset_name": "EXPEDIA GROUP INC CMN", "eif": null, "value": null, "income_types": null, "other_income_spec": null, "amount_of_income": null, "transaction": null},
    {"kind": "asset", "owner": "SP", "asset_name": "EXPEDITORS INTERNATIONAL OF WA CMN", "eif": null, "value": null, "income_types": null, "other_income_spec": null, "amount_of_income": null, "transaction": null},
    {"kind": "asset", "owner": "SP", "asset_name": "EXTRA SPACE STORAGE INC. CMN", "eif": null, "value": null, "income_types": null, "other_income_spec": null, "amount_of_income": null, "transaction": null},
    {"kind": "asset", "owner": "SP", "asset_name": "EXTRACTION OIL & GAS INC CMN", "eif": null, "value": null, "income_types": null, "other_income_spec": null, "amount_of_income": null, "transaction": null},
    {"kind": "asset", "owner": "SP", "asset_name": "EXXON MOBIL CORPORATION CMN", "eif": null, "value": null, "income_types": null, "other_income_spec": null, "amount_of_income": null, "transaction": null},
    {"kind": "asset", "owner": "SP", "asset_name": "F5 NETWORKS, INC. CMN", "eif": null, "value": null, "income_types": null, "other_income_spec": null, "amount_of_income": null, "transaction": null},
    {"kind": "asset", "owner": "SP", "asset_name": "FACEBOOK, INC. CMN CLASS A", "eif": null, "value": null, "income_types": null, "other_income_spec": null, "amount_of_income": null, "transaction": null},
    {"kind": "asset", "owner": "SP", "asset_name": "FAIR ISAAC CORP CMN", "eif": null, "value": null, "income_types": null, "other_income_spec": null, "amount_of_income": null, "transaction": null},
    {"kind": "asset", "owner": "SP", "asset_name": "FASTENAL COMPANY CMN", "eif": null, "value": null, "income_types": null, "other_income_spec": null, "amount_of_income": null, "transaction": null},
    {"kind": "asset", "owner": "SP", "asset_name": "FEDERAL RLTY INVT TR REIT CMN", "eif": null, "value": null, "income_types": null, "other_income_spec": null, "amount_of_income": null, "transaction": null}
  ],
  "free_text": null,
  "uncertainties": [
    {"row": null, "field": "row_count", "note": "84 asset rows read; scan is heavily degraded and consecutive similar rows (DUKE ENERGY/DUKE REALTY, and two adjacent DUPONT DE NEMOURS entries) could not be perfectly resolved, so total count may be off by 1-2"},
    {"row": null, "field": "amount_of_income/transaction", "read": "grids present but undecoded", "note": "same as page 55: Amount-of-Income value-matrix and Transaction Summary (P/S/E) X-marks visible but not assignable to a single column without off-by-one error; left null"},
    {"row": null, "field": "owner", "read": "SP (all rows)", "note": "SP/DC/JT column reads SP on every row (Mita Ahuja trust); not individually re-verified"},
    {"row": 6, "field": "asset_name", "read": "CORTEVA, INC. CMN", "note": "smudged; best-effort ID between CORNING and COSTCO"},
    {"row": 9, "field": "asset_name", "read": "CAMPBELL CNTY KY SCH DIST FIN CORP REV ... 12/01/24 ... PRERE 12/01/19", "note": "municipal bond, heavily illegible; issuer/rate/series best-effort, contains 'CAMPBELL CY M&M'"},
    {"row": 40, "field": "asset_name", "read": "DUKE REALTY CORPORATION CMN", "note": "low confidence; may not be a separate row"},
    {"row": 42, "field": "asset_name", "read": "DUPONT DE NEMOURS, INC. CMN", "note": "appears as a second DuPont row immediately after row 41; possible duplicate/legacy listing, transcribed as seen"},
    {"row": 70, "field": "asset_name", "read": "EVERGY, INC. CMN", "note": "smudged; best-effort between ETSY and EXACT SCIENCES"},
    {"row": 72, "field": "asset_name", "read": "EXELIXIS, INC. CMN", "note": "distinguished from EXELON (row 73) by ', INC.' suffix; low confidence"},
    {"row": 82, "field": "asset_name", "read": "FAIR ISAAC CORP CMN", "note": "renders like 'FAIR BANC'; identified as FAIR ISAAC by alphabetical position between FACEBOOK and FASTENAL; low confidence"},
    {"row": null, "field": "asset_name", "note": "municipal-bond rows (EPHRATA, EXETER TWP) have partially legible rate/date/series details"}
  ],
  "page_confidence": "low"
}
