{
  "pdf_page": 63,
  "printed_label": "Page 63 of 327",
  "section": "SCHEDULE A - ASSETS & \"UNEARNED INCOME\"",
  "page_type": "schedule_a",
  "filer": "Rohit Khanna",
  "rows": [
    {"kind": "asset", "owner": "DC", "asset_name": "RAYMOND JAMES FINANCIAL, INC. CMN", "value": "$1,001-$15,000", "income_types": ["DIVIDENDS"], "other_income_spec": null, "amount_of_income": "None", "transaction": "P,S"},
    {"kind": "asset", "owner": "DC", "asset_name": "REALTY INCOME CORP 3.1% 12/15/2029 USD", "value": "None", "income_types": ["NONE"], "other_income_spec": null, "amount_of_income": "None", "transaction": "P"},
    {"kind": "asset", "owner": "DC", "asset_name": "REALTY INCOME CORP 3.1% 12/15/2029 USD SR LIEN", "value": "$1,001-$15,000", "income_types": ["INTEREST"], "other_income_spec": null, "amount_of_income": "$1-$200", "transaction": null},
    {"kind": "asset", "owner": "DC", "asset_name": "REALTY INCOME CORP 4.625% 11/01/2025 USD", "value": "None", "income_types": ["NONE"], "other_income_spec": null, "amount_of_income": "None", "transaction": "P"},
    {"kind": "asset", "owner": "DC", "asset_name": "REALTY INCOME CORP 4.625% 11/01/2025 USD SR LIE", "value": "$1,001-$15,000", "income_types": ["INTEREST"], "other_income_spec": null, "amount_of_income": "$1-$200", "transaction": null},
    {"kind": "asset", "owner": "DC", "asset_name": "REALTY INCOME CORPORATION CMN", "value": "None", "income_types": ["DIVIDENDS"], "other_income_spec": null, "amount_of_income": "None", "transaction": "P,S"},
    {"kind": "asset", "owner": "DC", "asset_name": "REGENCY CENTERS CORPORATION CMN", "value": "None", "income_types": ["DIVIDENDS"], "other_income_spec": null, "amount_of_income": "None", "transaction": "S"},
    {"kind": "asset", "owner": "DC", "asset_name": "REGENERON PHARMACEUTICAL INC CMN", "value": "$1,001-$15,000", "income_types": ["CAPITAL GAINS"], "other_income_spec": null, "amount_of_income": "$1,001-$2,500", "transaction": "P,S,S(part)"},
    {"kind": "asset", "owner": "DC", "asset_name": "REGIONS FINANCIAL CORPORATION CMN", "value": "None", "income_types": ["DIVIDENDS"], "other_income_spec": null, "amount_of_income": "None", "transaction": "P,S"},
    {"kind": "asset", "owner": "DC", "asset_name": "REPUBLIC SERVICES INC CMN", "value": "$1,001-$15,000", "income_types": ["DIVIDENDS"], "other_income_spec": null, "amount_of_income": "None", "transaction": "P,S"},
    {"kind": "asset", "owner": "DC", "asset_name": "RESMED INC. CMN", "value": "$1,001-$15,000", "income_types": ["DIVIDENDS"], "other_income_spec": null, "amount_of_income": "None", "transaction": "P,S"},
    {"kind": "asset", "owner": "DC", "asset_name": "REVITY INC CMN", "value": "None", "income_types": ["DIVIDENDS"], "other_income_spec": null, "amount_of_income": "None", "transaction": "P,S"},
    {"kind": "asset", "owner": "DC", "asset_name": "REYNOLDS AMERICAN INC 4.45% 06/12/2025 USD", "value": "None", "income_types": ["NONE"], "other_income_spec": null, "amount_of_income": "None", "transaction": "P"},
    {"kind": "asset", "owner": "DC", "asset_name": "REYNOLDS AMERICAN INC 4.45% 06/12/2025 USD SR L", "value": "$1,001-$15,000", "income_types": ["INTEREST"], "other_income_spec": null, "amount_of_income": "$201-$1,000", "transaction": null},
    {"kind": "asset", "owner": "DC", "asset_name": "ROBERT HALF INC CMN", "value": "$1,001-$15,000", "income_types": ["DIVIDENDS"], "other_income_spec": null, "amount_of_income": "None", "transaction": "P"},
    {"kind": "asset", "owner": "DC", "asset_name": "ROBERT HALF INTERNATIONAL INC. CMN", "value": "None", "income_types": ["NONE"], "other_income_spec": null, "amount_of_income": "None", "transaction": "P,S"},
    {"kind": "asset", "owner": "DC", "asset_name": "ROCKWELL AUTOMATION INC CMN", "value": "$1,001-$15,000", "income_types": ["DIVIDENDS", "CAPITAL GAINS"], "other_income_spec": null, "amount_of_income": "$201-$1,000", "transaction": "P,S"},
    {"kind": "asset", "owner": "DC", "asset_name": "ROKU, INC. CMN", "value": "None", "income_types": ["NONE"], "other_income_spec": null, "amount_of_income": "None", "transaction": "S"},
    {"kind": "asset", "owner": "DC", "asset_name": "ROLLINS INC. REGOFF SCTASK0796638", "value": "$1,001-$15,000", "income_types": ["DIVIDENDS"], "other_income_spec": null, "amount_of_income": "$1-$200", "transaction": "P"},
    {"kind": "asset", "owner": "DC", "asset_name": "ROPER TECHNOLOGIES INC CMN", "value": "$1,001-$15,000", "income_types": ["DIVIDENDS", "CAPITAL GAINS"], "other_income_spec": null, "amount_of_income": "$201-$1,000", "transaction": "S,S(part)"}
  ],
  "free_text": null,
  "uncertainties": [
    {"row": 0, "field": "context", "read": "continuation of Ritu Ahuja 1995 Trust", "note": "No group header printed on this page; context inferred from surrounding attachment pages."},
    {"row": 5, "field": "asset_name", "read": "REALTY INCOME CORP 4.625% 11/01/2025 USD SR LIE", "note": "Printed name is truncated at the asset-name column edge."},
    {"row": 14, "field": "asset_name", "read": "REYNOLDS AMERICAN INC 4.45% 06/12/2025 USD SR L", "note": "Printed name is truncated at the asset-name column edge."}
  ],
  "page_confidence": "medium"
}
