{
  "pdf_page": 3,
  "printed_label": "Page 3 of 8",
  "section": "Periodic Transaction Report - attached transaction table",
  "page_type": "ptr",
  "filer": "Rohit Khanna",
  "rows": [
    {"kind": "group", "text": "M&R Trust Partnership"},
    {"kind": "tx", "owner": "SP", "asset_name": "ADOBE INC", "tx_type": "Purchase", "date": "09/23/2019", "notification_date": "10/02/2019", "amount": "$1,001-$15,000"},
    {"kind": "tx", "owner": "SP", "asset_name": "NVIDIA CORPORATION", "tx_type": "Sale", "date": "09/23/2019", "notification_date": "10/02/2019", "amount": "$1,001-$15,000"},
    {"kind": "tx", "owner": "SP", "asset_name": "ECOLAB INC", "tx_type": "Sale", "date": "09/06/2019", "notification_date": "10/02/2019", "amount": "$1,001-$15,000"},
    {"kind": "tx", "owner": "SP", "asset_name": "ALIGN TECHNOLOGY", "tx_type": "Purchase", "date": "09/06/2019", "notification_date": "10/02/2019", "amount": "$1,001-$15,000"},
    {"kind": "tx", "owner": "SP", "asset_name": "S&P GLOBAL INC COM", "tx_type": "Sale", "date": "09/04/2019", "notification_date": "10/02/2019", "amount": "$1,001-$15,000"},
    {"kind": "tx", "owner": "SP", "asset_name": "INTUIT INC", "tx_type": "Purchase", "date": "09/04/2019", "notification_date": "10/02/2019", "amount": "$1,001-$15,000"},
    {"kind": "tx", "owner": "SP", "asset_name": "ESTEE LAUDER CO INC CL A", "tx_type": "Sale", "date": "09/04/2019", "notification_date": "10/02/2019", "amount": "$1,001-$15,000"},
    {"kind": "tx", "owner": "SP", "asset_name": "MS AUTO-CALLABLE BUFFERED JUMP ON SX5E (SPZRJ)", "tx_type": "Sale", "date": "09/19/2019", "notification_date": "10/02/2019", "amount": "$250,001-$500,000"}
  ],
  "free_text": null,
  "uncertainties": [],
  "page_confidence": "high"
}
