{
  "pdf_page": 251,
  "printed_label": "Page 251 of 326",
  "section": "SCHEDULE B - TRANSACTIONS",
  "page_type": "schedule_b",
  "filer": "Rohit Khanna",
  "rows": [
    {"kind": "tx", "owner": "SP", "asset_name": "AUTODESK, INC. CMN", "tx_type": "Purchase", "cap_gain_over_200": false, "partial_sale": false, "date": "9/29/2020", "notification_date": null, "amount": "$1,001-$15,000"},
    {"kind": "tx", "owner": "SP", "asset_name": "ADVANCE AUTO PARTS, INC. CMN", "tx_type": "Purchase", "cap_gain_over_200": false, "partial_sale": false, "date": "1/8/2020", "notification_date": null, "amount": "$1,001-$15,000"},
    {"kind": "tx", "owner": "SP", "asset_name": "OTIS LIMITED CMN", "tx_type": "Purchase", "cap_gain_over_200": false, "partial_sale": false, "date": "1/8/2020", "notification_date": null, "amount": "$1,001-$15,000"},
    {"kind": "tx", "owner": "SP", "asset_name": "GENERAL DYNAMICS CORP. CMN", "tx_type": "Purchase", "cap_gain_over_200": false, "partial_sale": false, "date": "6/23/2020", "notification_date": null, "amount": "$1,001-$15,000"},
    {"kind": "tx", "owner": "SP", "asset_name": "EXPEDITORS INTERNATIONAL OF WA CMN", "tx_type": "Purchase", "cap_gain_over_200": false, "partial_sale": false, "date": "1/8/2020", "notification_date": null, "amount": "$1,001-$15,000"},
    {"kind": "tx", "owner": "SP", "asset_name": "PLAINS ALL AMERICAN PIPELINE L.P. COMMON UNITS", "tx_type": "Purchase", "cap_gain_over_200": false, "partial_sale": false, "date": "6/30/2020", "notification_date": null, "amount": "$1,001-$15,000"},
    {"kind": "tx", "owner": "SP", "asset_name": "FORTINET, INC. CMN", "tx_type": "Purchase", "cap_gain_over_200": false, "partial_sale": false, "date": "1/8/2020", "notification_date": null, "amount": "$1,001-$15,000"},
    {"kind": "tx", "owner": "SP", "asset_name": "LIBERTY GLOBAL, PLC CMN CLASS A", "tx_type": "Purchase", "cap_gain_over_200": false, "partial_sale": false, "date": "3/5/2020", "notification_date": null, "amount": "$1,001-$15,000"},
    {"kind": "tx", "owner": "SP", "asset_name": "XEROX HOLDINGS CORP CMN", "tx_type": "Purchase", "cap_gain_over_200": false, "partial_sale": false, "date": "3/5/2020", "notification_date": null, "amount": "$1,001-$15,000"},
    {"kind": "tx", "owner": "SP", "asset_name": "REGENCY CENTERS CORPORATION CMN", "tx_type": "Purchase", "cap_gain_over_200": false, "partial_sale": false, "date": "5/20/2020", "notification_date": null, "amount": "$1,001-$15,000"},
    {"kind": "tx", "owner": "SP", "asset_name": "DUNKIN BRANDS GROUP INC CMN", "tx_type": "Purchase", "cap_gain_over_200": false, "partial_sale": false, "date": "1/8/2020", "notification_date": null, "amount": "$1,001-$15,000"},
    {"kind": "tx", "owner": "SP", "asset_name": "CITRIX SYSTEMS INC CMN", "tx_type": "Purchase", "cap_gain_over_200": false, "partial_sale": false, "date": "1/8/2020", "notification_date": null, "amount": "$1,001-$15,000"},
    {"kind": "tx", "owner": "SP", "asset_name": "W.R. GRACE & CO (NEW) CMN", "tx_type": "Purchase", "cap_gain_over_200": false, "partial_sale": false, "date": "9/29/2020", "notification_date": null, "amount": "$1,001-$15,000"},
    {"kind": "tx", "owner": "SP", "asset_name": "WATERS CORPORATION COMMON STOCK", "tx_type": "Purchase", "cap_gain_over_200": false, "partial_sale": false, "date": "7/28/2020", "notification_date": null, "amount": "$1,001-$15,000"},
    {"kind": "tx", "owner": "SP", "asset_name": "ESSEX PROPERTY TRUST INC CMN", "tx_type": "Purchase", "cap_gain_over_200": false, "partial_sale": false, "date": "11/3/2020", "notification_date": null, "amount": "$1,001-$15,000"},
    {"kind": "tx", "owner": "SP", "asset_name": "WORKDAY, INC. CMN CLASS A", "tx_type": "Purchase", "cap_gain_over_200": false, "partial_sale": false, "date": "9/29/2020", "notification_date": null, "amount": "$1,001-$15,000"},
    {"kind": "tx", "owner": "SP", "asset_name": "AMERISOURCEBERGEN CORPORATION CMN", "tx_type": "Purchase", "cap_gain_over_200": false, "partial_sale": false, "date": "3/5/2020", "notification_date": null, "amount": "$1,001-$15,000"},
    {"kind": "tx", "owner": "SP", "asset_name": "LIONS GATE ENTERTAINMENT CORP. CMN CLASS A", "tx_type": "Purchase", "cap_gain_over_200": false, "partial_sale": false, "date": "3/5/2020", "notification_date": null, "amount": "$1,001-$15,000"},
    {"kind": "tx", "owner": "SP", "asset_name": "CVS HEALTH CORP CMN", "tx_type": "Purchase", "cap_gain_over_200": false, "partial_sale": false, "date": "2/11/2020", "notification_date": null, "amount": "$1,001-$15,000"},
    {"kind": "tx", "owner": "SP", "asset_name": "MOSAIC COMPANY (THE) CMN", "tx_type": "Purchase", "cap_gain_over_200": false, "partial_sale": false, "date": "6/23/2020", "notification_date": null, "amount": "$1,001-$15,000"},
    {"kind": "tx", "owner": "SP", "asset_name": "AXIS CAPITAL HOLDINGS LIMITED CMN", "tx_type": "Purchase", "cap_gain_over_200": false, "partial_sale": false, "date": "5/20/2020", "notification_date": null, "amount": "$1,001-$15,000"},
    {"kind": "tx", "owner": "SP", "asset_name": "NEWS CORPORATION CMN CLASS A", "tx_type": "Purchase", "cap_gain_over_200": false, "partial_sale": false, "date": "1/8/2020", "notification_date": null, "amount": "$1,001-$15,000"},
    {"kind": "tx", "owner": "SP", "asset_name": "PACWEST BANCORP CMN", "tx_type": "Purchase", "cap_gain_over_200": false, "partial_sale": false, "date": "9/29/2020", "notification_date": null, "amount": "$1,001-$15,000"},
    {"kind": "tx", "owner": "SP", "asset_name": "CORTEVA, INC. CMN", "tx_type": "Purchase", "cap_gain_over_200": false, "partial_sale": false, "date": "2/11/2020", "notification_date": null, "amount": "$1,001-$15,000"},
    {"kind": "tx", "owner": "SP", "asset_name": "STERLING BANCORP CMN", "tx_type": "Purchase", "cap_gain_over_200": false, "partial_sale": false, "date": "3/5/2020", "notification_date": null, "amount": "$1,001-$15,000"},
    {"kind": "tx", "owner": "SP", "asset_name": "ACTIVISION BLIZZARD, INC CMN", "tx_type": "Purchase", "cap_gain_over_200": false, "partial_sale": false, "date": "3/5/2020", "notification_date": null, "amount": "$1,001-$15,000"},
    {"kind": "tx", "owner": "SP", "asset_name": "MID-AMERICA APT CMNTYS INC CMN", "tx_type": "Purchase", "cap_gain_over_200": false, "partial_sale": false, "date": "3/5/2020", "notification_date": null, "amount": "$1,001-$15,000"}
  ],
  "free_text": null,
  "uncertainties": [],
  "page_confidence": "high"
}
