{
  "pdf_page": 64,
  "printed_label": "Page 64 of 367",
  "section": "SCHEDULE A - ASSETS & \"UNEARNED INCOME\"",
  "page_type": "schedule_a",
  "filer": "Rohit Khanna",
  "rows": [
    {"kind":"asset","owner":"SP","asset_name":"ALPHABET INC. CMN CLASS A","eif":false,"value":"None","income_types":["NONE"],"other_income_spec":null,"amount_of_income":"None","transaction":"P,S,S(part)"},
    {"kind":"asset","owner":"SP","asset_name":"ALPHABET INC. CMN CLASS C","eif":false,"value":"None","income_types":["NONE"],"other_income_spec":null,"amount_of_income":"None","transaction":"P,S,S(part)"},
    {"kind":"asset","owner":"SP","asset_name":"ALTERYX, INC. CMN CLASS A","eif":false,"value":"None","income_types":["NONE"],"other_income_spec":null,"amount_of_income":"None","transaction":"P,S"},
    {"kind":"asset","owner":"SP","asset_name":"ALTRIA GROUP, INC. CMN","eif":false,"value":"$15,001-$50,000","income_types":["DIVIDENDS"],"other_income_spec":null,"amount_of_income":"$5,001-$15,000","transaction":"P,S,S(part)"},
    {"kind":"asset","owner":"SP","asset_name":"AMAZON.COM INC CMN","eif":false,"value":"$100,001-$250,000","income_types":["NONE"],"other_income_spec":null,"amount_of_income":"None","transaction":"P,S,S(part)"},
    {"kind":"asset","owner":"SP","asset_name":"AMAZON.COM INC SRS 28153166","eif":false,"value":"None","income_types":["NONE"],"other_income_spec":null,"amount_of_income":"None","transaction":"S,S(part)"},
    {"kind":"asset","owner":"SP","asset_name":"AMCOR PLC CMN","eif":false,"value":"None","income_types":["DIVIDENDS"],"other_income_spec":null,"amount_of_income":"None","transaction":"P,S"},
    {"kind":"asset","owner":"SP","asset_name":"AMEDISYS, INC. CMN","eif":false,"value":"$1,001-$15,000","income_types":["NONE"],"other_income_spec":null,"amount_of_income":"None","transaction":null},
    {"kind":"asset","owner":"SP","asset_name":"AMERCO CMN","eif":false,"value":"None","income_types":["NONE"],"other_income_spec":null,"amount_of_income":"None","transaction":"P,S"},
    {"kind":"asset","owner":"SP","asset_name":"AMERICAN AIRLINES GROUP INC CMN","eif":false,"value":"None","income_types":["NONE"],"other_income_spec":null,"amount_of_income":"None","transaction":"P,S,S(part)"},
    {"kind":"asset","owner":"SP","asset_name":"AMERICAN EXPRESS CO. CMN","eif":false,"value":"$15,001-$50,000","income_types":["DIVIDENDS"],"other_income_spec":null,"amount_of_income":"None","transaction":"P,S,S(part)"},
    {"kind":"asset","owner":"SP","asset_name":"AMERICAN INTL GROUP, INC. CMN","eif":false,"value":"$15,001-$50,000","income_types":["DIVIDENDS"],"other_income_spec":null,"amount_of_income":"$5,001-$15,000","transaction":"P,S,S(part)"},
    {"kind":"asset","owner":"SP","asset_name":"AMERICAN TOWER CORPORATION CMN","eif":false,"value":"$15,001-$50,000","income_types":["DIVIDENDS"],"other_income_spec":null,"amount_of_income":"None","transaction":"P,S,S(part)"},
    {"kind":"asset","owner":"SP","asset_name":"AMERIPRISE FINANCIAL, INC. CMN","eif":false,"value":"$15,001-$50,000","income_types":["DIVIDENDS"],"other_income_spec":null,"amount_of_income":"None","transaction":"P,S,S(part)"},
    {"kind":"asset","owner":"SP","asset_name":"AMERISOURCEBERGEN CORPORATION CMN","eif":false,"value":"None","income_types":["DIVIDENDS"],"other_income_spec":null,"amount_of_income":"$1,001-$2,500","transaction":"S"},
    {"kind":"asset","owner":"SP","asset_name":"AMETEK INC (NEW) CMN","eif":false,"value":"$1,001-$15,000","income_types":["DIVIDENDS"],"other_income_spec":null,"amount_of_income":"None","transaction":"P,S,S(part)"},
    {"kind":"asset","owner":"SP","asset_name":"AMGEN INC. CMN","eif":false,"value":"$1,001-$15,000","income_types":["DIVIDENDS"],"other_income_spec":null,"amount_of_income":"$5,001-$15,000","transaction":"P,S,S(part)"},
    {"kind":"asset","owner":"SP","asset_name":"AMPHENOL CORP CL-A (NEW) CMN CLASS A","eif":false,"value":"$15,001-$50,000","income_types":["DIVIDENDS"],"other_income_spec":null,"amount_of_income":"None","transaction":"P,S"},
    {"kind":"asset","owner":"SP","asset_name":"ANALOG DEVICES, INC. CMN","eif":false,"value":"$1,001-$15,000","income_types":["DIVIDENDS"],"other_income_spec":null,"amount_of_income":"None","transaction":"P,S,S(part)"},
    {"kind":"asset","owner":"SP","asset_name":"ANSYS, INC. CMN","eif":false,"value":"$1,001-$15,000","income_types":["NONE"],"other_income_spec":null,"amount_of_income":"None","transaction":"P,S,S(part)"},
    {"kind":"asset","owner":"SP","asset_name":"ANTHEM, INC. CMN","eif":false,"value":"None","income_types":["DIVIDENDS"],"other_income_spec":null,"amount_of_income":"None","transaction":"P"},
    {"kind":"asset","owner":"SP","asset_name":"AON PUBLIC LIMITED COMPANY CMN","eif":false,"value":"$15,001-$50,000","income_types":["DIVIDENDS"],"other_income_spec":null,"amount_of_income":"$201-$1,000","transaction":"P,S,S(part)"},
    {"kind":"asset","owner":"SP","asset_name":"APOLLO GLOBAL MANAGEMENT INC CMN","eif":false,"value":"$1,001-$15,000","income_types":["DIVIDENDS"],"other_income_spec":null,"amount_of_income":"$1,001-$2,500","transaction":"S,S(part)"},
    {"kind":"asset","owner":"SP","asset_name":"APPLE INC. CMN","eif":false,"value":"$500,001-$1,000,000","income_types":["DIVIDENDS"],"other_income_spec":null,"amount_of_income":"None","transaction":"P,S(part)"},
    {"kind":"asset","owner":"SP","asset_name":"APPLIED MATERIALS INC CMN","eif":false,"value":"$15,001-$50,000","income_types":["DIVIDENDS"],"other_income_spec":null,"amount_of_income":"None","transaction":"P,S,S(part)"}
  ],
  "free_text": null,
  "uncertainties": [{"field":"checkbox_columns","note":"Dense scanned grid; several value and amount X marks are faint and close to gridlines."}],
  "page_confidence": "medium"
}
