{
  "pdf_page": 40,
  "printed_label": "Page 40 of 149",
  "section": "Schedule A: Assets and \"Unearned\" Income",
  "page_type": "schedule_a",
  "filer": "Rohit Khanna",
  "layout_note": "Typed spreadsheet-style Schedule A grid (attachment format). Columns: SP/DC/JT, Asset Name, EIF (blank), Block B Value of Asset (12 Min/Max columns: 0; 1-1,000; 1,001-15,000; 15,001-50,000; 50,001-100,000; 100,001-250,000; 250,001-500,000; 500,001-1,000,000; 1,000,001-5,000,000; 5,000,001-25,000,000; 25,000,001-50,000,000; 50,000,001-2,000,000,000), Block C Type of Income (None/Dividends/Rent/Interest/Capital Gains/Excepted-Blind Trust/Tax Deferred/Partnership Income), Block D Amount of Income (Min/Max columns: 0; 0-200; 201-1,000; 1,001-2,500; 2,501-5,000; 5,001-15,000; 15,001-50,000; 50,001-100,000; 100,001-1,000,000; 1,000,001-5,000,000; 5,000,001-1,000,000,000; Spouse/DC Income over 1000000), Block E Transaction (P, S, S(part), or E). Note: the printed Min for the second Block D column reads '0' (Max 200); transcribed here as the standard $1-$200 bucket. Group header carries left-margin ID 1099. X-mark column assignments verified by pixel-centroid measurement against grid borders.",
  "rows": [
    {"kind": "group", "text": "Ritu Ahuja 1995 Trust", "note": "left-margin ID 1099"},
    {"kind": "asset", "owner": "SP", "asset_name": "DISCOVER FINANCIAL SERVICES CMN", "value": "$1,001-$15,000", "income_types": ["Dividends"], "other_income_spec": null, "amount_of_income": "$1-$200", "transaction": null},
    {"kind": "asset", "owner": "SP", "asset_name": "DISCOVERY INC - A CMN SERIES A", "value": "$1-$1,000", "income_types": ["None"], "other_income_spec": null, "amount_of_income": "None", "transaction": "S(part)"},
    {"kind": "asset", "owner": "SP", "asset_name": "DISCOVERY INC CMN", "value": "$1-$1,000", "income_types": ["None"], "other_income_spec": null, "amount_of_income": "None", "transaction": "S(part)"},
    {"kind": "asset", "owner": "SP", "asset_name": "DOLLAR GENERAL CORPORATION CMN", "value": "$1,001-$15,000", "income_types": ["Dividends"], "other_income_spec": null, "amount_of_income": "$1-$200", "transaction": null},
    {"kind": "asset", "owner": "SP", "asset_name": "DOLLAR TREE STORES, INC. CMN", "value": "$1,001-$15,000", "income_types": ["None"], "other_income_spec": null, "amount_of_income": "None", "transaction": null},
    {"kind": "asset", "owner": "SP", "asset_name": "DOMINION ENERGY INC CMN", "value": "$1,001-$15,000", "income_types": ["Dividends"], "other_income_spec": null, "amount_of_income": "$1-$200", "transaction": null},
    {"kind": "asset", "owner": "SP", "asset_name": "DOMINO'S PIZZA, INC. CMN", "value": "None", "income_types": ["None"], "other_income_spec": null, "amount_of_income": "None", "transaction": null},
    {"kind": "asset", "owner": "SP", "asset_name": "DOUGLAS EMMETT, INC. CMN", "value": "$1-$1,000", "income_types": ["Dividends"], "other_income_spec": null, "amount_of_income": "$1-$200", "transaction": null},
    {"kind": "asset", "owner": "SP", "asset_name": "DOVER CORPORATION CMN", "value": "$1,001-$15,000", "income_types": ["Dividends"], "other_income_spec": null, "amount_of_income": "$1-$200", "transaction": null},
    {"kind": "asset", "owner": "SP", "asset_name": "DOW CHEMICAL CO CMN", "value": "None", "income_types": ["Dividends"], "other_income_spec": null, "amount_of_income": "$1-$200", "transaction": null},
    {"kind": "asset", "owner": "SP", "asset_name": "DOWDUPONT INC. CMN", "value": "$1,001-$15,000", "income_types": ["Dividends"], "other_income_spec": null, "amount_of_income": "$1-$200", "transaction": null},
    {"kind": "asset", "owner": "SP", "asset_name": "DR PEPPER SNAPPLE GROUP, INC. CMN", "value": "None", "income_types": ["Dividends"], "other_income_spec": null, "amount_of_income": "$1-$200", "transaction": null},
    {"kind": "asset", "owner": "SP", "asset_name": "DTE ENERGY COMPANY CMN", "value": "$1-$1,000", "income_types": ["Dividends"], "other_income_spec": null, "amount_of_income": "$1-$200", "transaction": null},
    {"kind": "asset", "owner": "SP", "asset_name": "DUKE ENERGY CORPORATION CMN", "value": "$1,001-$15,000", "income_types": ["Dividends"], "other_income_spec": null, "amount_of_income": "$1-$200", "transaction": "P"},
    {"kind": "asset", "owner": "SP", "asset_name": "DUKE REALTY CORPORATION CMN", "value": "$1-$1,000", "income_types": ["Dividends"], "other_income_spec": null, "amount_of_income": "$1-$200", "transaction": null},
    {"kind": "asset", "owner": "SP", "asset_name": "DXC TECHNOLOGY COMPANY CMN", "value": "$1,001-$15,000", "income_types": ["Dividends"], "other_income_spec": null, "amount_of_income": "$1-$200", "transaction": "P"},
    {"kind": "asset", "owner": "SP", "asset_name": "E*TRADE FINANCIAL CORPORATION CMN", "value": "$1,001-$15,000", "income_types": ["None"], "other_income_spec": null, "amount_of_income": "None", "transaction": null},
    {"kind": "asset", "owner": "SP", "asset_name": "E.I. DU PONT DE NEMOURS AND CO CMN", "value": "None", "income_types": ["Dividends"], "other_income_spec": null, "amount_of_income": "$1-$200", "transaction": null},
    {"kind": "asset", "owner": "SP", "asset_name": "EAST WEST BANCORP INC CMN", "value": "$1-$1,000", "income_types": ["Dividends"], "other_income_spec": null, "amount_of_income": "$1-$200", "transaction": null},
    {"kind": "asset", "owner": "SP", "asset_name": "EASTMAN CHEMICAL COMPANY CMN", "value": "$1-$1,000", "income_types": ["Dividends"], "other_income_spec": null, "amount_of_income": "$1-$200", "transaction": null},
    {"kind": "asset", "owner": "SP", "asset_name": "EATON CORP PLC CMN", "value": "$1,001-$15,000", "income_types": ["Dividends", "Capital Gains"], "other_income_spec": null, "amount_of_income": "$1-$200", "transaction": "P, S(part)"},
    {"kind": "asset", "owner": "SP", "asset_name": "EBAY INC. CMN", "value": "$1,001-$15,000", "income_types": ["None"], "other_income_spec": null, "amount_of_income": "None", "transaction": "P"},
    {"kind": "asset", "owner": "SP", "asset_name": "ECOLAB INC. CMN", "value": "$1,001-$15,000", "income_types": ["Dividends"], "other_income_spec": null, "amount_of_income": "$1-$200", "transaction": null},
    {"kind": "asset", "owner": "SP", "asset_name": "EDISON INTERNATIONAL CMN", "value": "$1-$1,000", "income_types": ["Dividends"], "other_income_spec": null, "amount_of_income": "$1-$200", "transaction": null},
    {"kind": "asset", "owner": "SP", "asset_name": "EDWARDS LIFESCIENCES CORPORATI CMN", "value": "$1,001-$15,000", "income_types": ["None"], "other_income_spec": null, "amount_of_income": "None", "transaction": "S(part)"},
    {"kind": "asset", "owner": "SP", "asset_name": "ELECTRONIC ARTS CMN", "value": "$1,001-$15,000", "income_types": ["Capital Gains"], "other_income_spec": null, "amount_of_income": "$1-$200", "transaction": "P"},
    {"kind": "asset", "owner": "SP", "asset_name": "ELI LILLY & CO CMN", "value": "$1,001-$15,000", "income_types": ["Dividends"], "other_income_spec": null, "amount_of_income": "$1-$200", "transaction": "P"},
    {"kind": "asset", "owner": "SP", "asset_name": "EMERSON ELECTRIC CO. CMN", "value": "$1,001-$15,000", "income_types": ["Dividends"], "other_income_spec": null, "amount_of_income": "$1-$200", "transaction": "P"},
    {"kind": "asset", "owner": "SP", "asset_name": "ENDO INTERNATIONAL PLC CMN", "value": "$1-$1,000", "income_types": ["None"], "other_income_spec": null, "amount_of_income": "None", "transaction": null},
    {"kind": "asset", "owner": "SP", "asset_name": "ENERGEN CORP CMN", "value": "$1-$1,000", "income_types": ["None"], "other_income_spec": null, "amount_of_income": "None", "transaction": null},
    {"kind": "asset", "owner": "SP", "asset_name": "ENERGIZER HOLDINGS, INC. CMN", "value": "$1-$1,000", "income_types": ["Dividends", "Capital Gains"], "other_income_spec": null, "amount_of_income": "$1-$200", "transaction": null},
    {"kind": "asset", "owner": "SP", "asset_name": "ENERGY TRANSFER PARTNERS, L.P. CMN", "value": "$100,001-$250,000", "income_types": ["Capital Gains", "Partnership Income"], "other_income_spec": null, "amount_of_income": "$15,001-$50,000", "transaction": "S(part)"},
    {"kind": "asset", "owner": "SP", "asset_name": "ENERGY TRANSFER, LP CMN", "value": "None", "income_types": ["None"], "other_income_spec": null, "amount_of_income": "None", "transaction": null},
    {"kind": "asset", "owner": "SP", "asset_name": "ENTERGY CORPORATION CMN", "value": "$1-$1,000", "income_types": ["Dividends"], "other_income_spec": null, "amount_of_income": "$1-$200", "transaction": null},
    {"kind": "asset", "owner": "SP", "asset_name": "ENTERPRISE PRODUCTS PART L.P CMN", "value": "$100,001-$250,000", "income_types": ["Capital Gains", "Partnership Income"], "other_income_spec": null, "amount_of_income": "$50,001-$100,000", "transaction": "S(part)"},
    {"kind": "asset", "owner": "SP", "asset_name": "ENVISION HEALTHCARE CORPORATIO CMN", "value": "None", "income_types": ["None"], "other_income_spec": null, "amount_of_income": "None", "transaction": null},
    {"kind": "asset", "owner": "SP", "asset_name": "EOG RESOURCES INC CMN", "value": "$1,001-$15,000", "income_types": ["Dividends"], "other_income_spec": null, "amount_of_income": "$1-$200", "transaction": "P, S(part)"},
    {"kind": "asset", "owner": "SP", "asset_name": "EPR PROPERTIES CMN", "value": "None", "income_types": ["Dividends"], "other_income_spec": null, "amount_of_income": "$1-$200", "transaction": null},
    {"kind": "asset", "owner": "SP", "asset_name": "EQT CORPORATION CMN", "value": "$1-$1,000", "income_types": ["Dividends"], "other_income_spec": null, "amount_of_income": "$1-$200", "transaction": null},
    {"kind": "asset", "owner": "SP", "asset_name": "EQT MIDSTREAM PARTNERS, LP CMN", "value": "$50,001-$100,000", "income_types": ["Capital Gains", "Partnership Income"], "other_income_spec": null, "amount_of_income": "None", "transaction": "S(part)"},
    {"kind": "asset", "owner": "SP", "asset_name": "EQUIFAX INC. CMN", "value": "$1,001-$15,000", "income_types": ["Dividends"], "other_income_spec": null, "amount_of_income": "$1-$200", "transaction": null},
    {"kind": "asset", "owner": "SP", "asset_name": "EQUINIX, INC. REIT", "value": "$1,001-$15,000", "income_types": ["Dividends"], "other_income_spec": null, "amount_of_income": "$1-$200", "transaction": "P"},
    {"kind": "asset", "owner": "SP", "asset_name": "EQUITY RESIDENTIAL CMN", "value": "$1-$1,000", "income_types": ["Dividends"], "other_income_spec": null, "amount_of_income": "$1-$200", "transaction": null},
    {"kind": "asset", "owner": "SP", "asset_name": "ESSEX PROPERTY TRUST INC CMN", "value": "None", "income_types": ["Dividends"], "other_income_spec": null, "amount_of_income": "$1-$200", "transaction": null},
    {"kind": "asset", "owner": "SP", "asset_name": "ESTEE LAUDER COS INC CL-A CMN CLASS A", "value": "$1,001-$15,000", "income_types": ["Dividends"], "other_income_spec": null, "amount_of_income": "$1-$200", "transaction": "P"},
    {"kind": "asset", "owner": "SP", "asset_name": "EURONET WORLDWIDE INC CMN", "value": "$1-$1,000", "income_types": ["None"], "other_income_spec": null, "amount_of_income": "None", "transaction": null},
    {"kind": "asset", "owner": "SP", "asset_name": "EVEREST RE GROUP LTD CMN", "value": "$1-$1,000", "income_types": ["Dividends"], "other_income_spec": null, "amount_of_income": "$1-$200", "transaction": null},
    {"kind": "asset", "owner": "SP", "asset_name": "EVERSOURCE ENERGY CMN", "value": "$1,001-$15,000", "income_types": ["Dividends"], "other_income_spec": null, "amount_of_income": "$1-$200", "transaction": null},
    {"kind": "asset", "owner": "SP", "asset_name": "EXELIXIS, INC. CMN", "value": "None", "income_types": ["None"], "other_income_spec": null, "amount_of_income": "None", "transaction": null},
    {"kind": "asset", "owner": "SP", "asset_name": "EXELON CORPORATION CMN", "value": "$1,001-$15,000", "income_types": ["Dividends"], "other_income_spec": null, "amount_of_income": "$1-$200", "transaction": "P, S(part)"}
  ],
  "free_text": null,
  "uncertainties": [
    {"row": 40, "field": "amount_of_income", "read": "None", "note": "EQT MIDSTREAM PARTNERS has Capital Gains + Partnership Income marked in Block C but its Block D X sits squarely in the None column (verified by zoom and pixel measurement); transcribed as seen"}
  ],
  "page_confidence": "high"
}
