{
  "pdf_page": 47,
  "printed_label": "Page 47 of 309",
  "section": "Schedule A: Assets and Unearned Income",
  "page_type": "schedule_a",
  "filer": "Rohit Khanna",
  "layout_note": "Standard (non-transposed) typed attachment grid, 'Type of Income' block (Block C) for the same 46-asset C-block of the 'Ritu Ahuja 1994 Trust' as page 46 (CELANESE through CONOCOPHILLIPS). Income columns: None, Dividends, Rent, Interest, Capital Gains, Excepted/Blind Trust, Tax Deferred, Partnership Income. Only None, Dividends, Interest, and Capital Gains are marked anywhere on the page. No Value/Amount/Transaction columns (null). EIF empty. Two municipal bonds have 2-line names with the income X on the second line (CLARK CNTY -> Interest; CLEVELAND CNTY -> None). Marks located by blob-centroid pixel analysis and cross-checked against the full-page image row by row. All assets owner SP.",
  "rows": [
    {"kind": "group", "text": "Ritu Ahuja 1994 Trust"},
    {"kind": "asset", "owner": "SP", "asset_name": "CELANESE CORPORATION COMMON STOCK", "ticker": null, "eif": null, "value": null, "income_types": ["DIVIDENDS"], "other_income_spec": null, "amount_of_income": null, "transaction": null},
    {"kind": "asset", "owner": "SP", "asset_name": "CELGENE CORPORATION CMN", "ticker": null, "eif": null, "value": null, "income_types": ["NONE"], "other_income_spec": null, "amount_of_income": null, "transaction": null},
    {"kind": "asset", "owner": "SP", "asset_name": "CENTENE CORPORATION CMN", "ticker": null, "eif": null, "value": null, "income_types": ["NONE"], "other_income_spec": null, "amount_of_income": null, "transaction": null},
    {"kind": "asset", "owner": "SP", "asset_name": "CENTENNIAL RESOURCE DEVELOPMEN CMN", "ticker": null, "eif": null, "value": null, "income_types": ["NONE"], "other_income_spec": null, "amount_of_income": null, "transaction": null},
    {"kind": "asset", "owner": "SP", "asset_name": "CENTERPOINT ENERGY, INC CMN", "ticker": null, "eif": null, "value": null, "income_types": ["DIVIDENDS"], "other_income_spec": null, "amount_of_income": null, "transaction": null},
    {"kind": "asset", "owner": "SP", "asset_name": "CENTURYLINK INC CMN", "ticker": null, "eif": null, "value": null, "income_types": ["DIVIDENDS", "CAPITAL GAINS"], "other_income_spec": null, "amount_of_income": null, "transaction": null},
    {"kind": "asset", "owner": "SP", "asset_name": "CERNER CORPORATION CMN", "ticker": null, "eif": null, "value": null, "income_types": ["CAPITAL GAINS"], "other_income_spec": null, "amount_of_income": null, "transaction": null},
    {"kind": "asset", "owner": "SP", "asset_name": "CF INDUSTRIES HOLDINGS, INC. CMN", "ticker": null, "eif": null, "value": null, "income_types": ["DIVIDENDS", "CAPITAL GAINS"], "other_income_spec": null, "amount_of_income": null, "transaction": null},
    {"kind": "asset", "owner": "SP", "asset_name": "CHARLES RIV LABS INTL INC CMN", "ticker": null, "eif": null, "value": null, "income_types": ["NONE"], "other_income_spec": null, "amount_of_income": null, "transaction": null},
    {"kind": "asset", "owner": "SP", "asset_name": "CHARLES SCHWAB CORPORATION CMN", "ticker": null, "eif": null, "value": null, "income_types": ["DIVIDENDS", "CAPITAL GAINS"], "other_income_spec": null, "amount_of_income": null, "transaction": null},
    {"kind": "asset", "owner": "SP", "asset_name": "CHARTER COMMUNICATIONS, INC. CMN", "ticker": null, "eif": null, "value": null, "income_types": ["NONE"], "other_income_spec": null, "amount_of_income": null, "transaction": null},
    {"kind": "asset", "owner": "SP", "asset_name": "CHEMOURS COMPANY (THE) CMN", "ticker": null, "eif": null, "value": null, "income_types": ["DIVIDENDS"], "other_income_spec": null, "amount_of_income": null, "transaction": null},
    {"kind": "asset", "owner": "SP", "asset_name": "CHENIERE ENERGY, INC. CMN", "ticker": null, "eif": null, "value": null, "income_types": ["NONE"], "other_income_spec": null, "amount_of_income": null, "transaction": null},
    {"kind": "asset", "owner": "SP", "asset_name": "CHESAPEAKE ENERGY CORPORATION CMN", "ticker": null, "eif": null, "value": null, "income_types": ["NONE"], "other_income_spec": null, "amount_of_income": null, "transaction": null},
    {"kind": "asset", "owner": "SP", "asset_name": "CHEVRON CORPORATION CMN", "ticker": null, "eif": null, "value": null, "income_types": ["DIVIDENDS", "CAPITAL GAINS"], "other_income_spec": null, "amount_of_income": null, "transaction": null},
    {"kind": "asset", "owner": "SP", "asset_name": "CHIPOTLE MEXICAN GRILL, INC. CMN", "ticker": null, "eif": null, "value": null, "income_types": ["NONE"], "other_income_spec": null, "amount_of_income": null, "transaction": null},
    {"kind": "asset", "owner": "SP", "asset_name": "CHUBB LIMITED CMN", "ticker": null, "eif": null, "value": null, "income_types": ["DIVIDENDS"], "other_income_spec": null, "amount_of_income": null, "transaction": null},
    {"kind": "asset", "owner": "SP", "asset_name": "CHURCH & DWIGHT CO., INC. CMN", "ticker": null, "eif": null, "value": null, "income_types": ["DIVIDENDS"], "other_income_spec": null, "amount_of_income": null, "transaction": null},
    {"kind": "asset", "owner": "SP", "asset_name": "CIGNA CORP CMN", "ticker": null, "eif": null, "value": null, "income_types": ["NONE"], "other_income_spec": null, "amount_of_income": null, "transaction": null},
    {"kind": "asset", "owner": "SP", "asset_name": "CIGNA CORPORATION CMN", "ticker": null, "eif": null, "value": null, "income_types": ["DIVIDENDS"], "other_income_spec": null, "amount_of_income": null, "transaction": null},
    {"kind": "asset", "owner": "SP", "asset_name": "CIMAREX ENERGY CO. CMN", "ticker": null, "eif": null, "value": null, "income_types": ["DIVIDENDS"], "other_income_spec": null, "amount_of_income": null, "transaction": null},
    {"kind": "asset", "owner": "SP", "asset_name": "CINCINNATI FINANCIAL CRP CMN", "ticker": null, "eif": null, "value": null, "income_types": ["DIVIDENDS"], "other_income_spec": null, "amount_of_income": null, "transaction": null},
    {"kind": "asset", "owner": "SP", "asset_name": "CINTAS CORPORATION CMN", "ticker": null, "eif": null, "value": null, "income_types": ["DIVIDENDS"], "other_income_spec": null, "amount_of_income": null, "transaction": null},
    {"kind": "asset", "owner": "SP", "asset_name": "CISCO SYSTEMS, INC. CMN", "ticker": null, "eif": null, "value": null, "income_types": ["DIVIDENDS"], "other_income_spec": null, "amount_of_income": null, "transaction": null},
    {"kind": "asset", "owner": "SP", "asset_name": "CITIGROUP INC. CMN", "ticker": null, "eif": null, "value": null, "income_types": ["DIVIDENDS", "CAPITAL GAINS"], "other_income_spec": null, "amount_of_income": null, "transaction": null},
    {"kind": "asset", "owner": "SP", "asset_name": "CITIZENS FINANCIAL GROUP, INC. CMN", "ticker": null, "eif": null, "value": null, "income_types": ["DIVIDENDS", "CAPITAL GAINS"], "other_income_spec": null, "amount_of_income": null, "transaction": null},
    {"kind": "asset", "owner": "SP", "asset_name": "CITRIX SYSTEMS INC CMN", "ticker": null, "eif": null, "value": null, "income_types": ["DIVIDENDS"], "other_income_spec": null, "amount_of_income": null, "transaction": null},
    {"kind": "asset", "owner": "SP", "asset_name": "CLARK CNTY NEV SCH DIST GO 5% 06/15/19 JD GO LTD TAX REF BDS 2012A LT BEO", "ticker": null, "eif": null, "value": null, "income_types": ["INTEREST"], "other_income_spec": null, "amount_of_income": null, "transaction": null},
    {"kind": "asset", "owner": "SP", "asset_name": "CLEVELAND CNTY OK ED FACS REV 5.0000% 07/01/19-CA JJ REV BDS NORMAN PUB SCH PROJ 2014 BEO", "ticker": null, "eif": null, "value": null, "income_types": ["NONE"], "other_income_spec": null, "amount_of_income": null, "transaction": null},
    {"kind": "asset", "owner": "SP", "asset_name": "CLOROX CO (THE) (DELAWARE) CMN", "ticker": null, "eif": null, "value": null, "income_types": ["DIVIDENDS"], "other_income_spec": null, "amount_of_income": null, "transaction": null},
    {"kind": "asset", "owner": "SP", "asset_name": "CME GROUP INC. CMN CLASS A", "ticker": null, "eif": null, "value": null, "income_types": ["DIVIDENDS"], "other_income_spec": null, "amount_of_income": null, "transaction": null},
    {"kind": "asset", "owner": "SP", "asset_name": "CMS ENERGY CORPORATION CMN", "ticker": null, "eif": null, "value": null, "income_types": ["DIVIDENDS"], "other_income_spec": null, "amount_of_income": null, "transaction": null},
    {"kind": "asset", "owner": "SP", "asset_name": "CNA FINCL.CORP. CMN", "ticker": null, "eif": null, "value": null, "income_types": ["DIVIDENDS"], "other_income_spec": null, "amount_of_income": null, "transaction": null},
    {"kind": "asset", "owner": "SP", "asset_name": "COCA-COLA COMPANY (THE) CMN", "ticker": null, "eif": null, "value": null, "income_types": ["DIVIDENDS"], "other_income_spec": null, "amount_of_income": null, "transaction": null},
    {"kind": "asset", "owner": "SP", "asset_name": "COGNEX CORPORATION CMN", "ticker": null, "eif": null, "value": null, "income_types": ["DIVIDENDS"], "other_income_spec": null, "amount_of_income": null, "transaction": null},
    {"kind": "asset", "owner": "SP", "asset_name": "COGNIZANT TECHNOLOGY SOLUTIONS CORP CLASS A", "ticker": null, "eif": null, "value": null, "income_types": ["DIVIDENDS", "CAPITAL GAINS"], "other_income_spec": null, "amount_of_income": null, "transaction": null},
    {"kind": "asset", "owner": "SP", "asset_name": "COHERENT INC. CMN", "ticker": null, "eif": null, "value": null, "income_types": ["NONE"], "other_income_spec": null, "amount_of_income": null, "transaction": null},
    {"kind": "asset", "owner": "SP", "asset_name": "COLFAX CORPORATION CMN", "ticker": null, "eif": null, "value": null, "income_types": ["NONE"], "other_income_spec": null, "amount_of_income": null, "transaction": null},
    {"kind": "asset", "owner": "SP", "asset_name": "COLGATE-PALMOLIVE CO CMN", "ticker": null, "eif": null, "value": null, "income_types": ["DIVIDENDS", "CAPITAL GAINS"], "other_income_spec": null, "amount_of_income": null, "transaction": null},
    {"kind": "asset", "owner": "SP", "asset_name": "COLONY CAPITAL INC CMN", "ticker": null, "eif": null, "value": null, "income_types": ["NONE"], "other_income_spec": null, "amount_of_income": null, "transaction": null},
    {"kind": "asset", "owner": "SP", "asset_name": "COMCAST CORPORATION CMN CLASS A VOTING", "ticker": null, "eif": null, "value": null, "income_types": ["DIVIDENDS", "CAPITAL GAINS"], "other_income_spec": null, "amount_of_income": null, "transaction": null},
    {"kind": "asset", "owner": "SP", "asset_name": "COMERICA INCORPORATED CMN", "ticker": null, "eif": null, "value": null, "income_types": ["DIVIDENDS", "CAPITAL GAINS"], "other_income_spec": null, "amount_of_income": null, "transaction": null},
    {"kind": "asset", "owner": "SP", "asset_name": "COMMSCOPE HLDG CO INC CMN", "ticker": null, "eif": null, "value": null, "income_types": ["NONE"], "other_income_spec": null, "amount_of_income": null, "transaction": null},
    {"kind": "asset", "owner": "SP", "asset_name": "CONAGRA BRANDS INC CMN", "ticker": null, "eif": null, "value": null, "income_types": ["DIVIDENDS"], "other_income_spec": null, "amount_of_income": null, "transaction": null},
    {"kind": "asset", "owner": "SP", "asset_name": "CONCHO RESOURCES INC. CMN", "ticker": null, "eif": null, "value": null, "income_types": ["NONE"], "other_income_spec": null, "amount_of_income": null, "transaction": null},
    {"kind": "asset", "owner": "SP", "asset_name": "CONOCOPHILLIPS CMN", "ticker": null, "eif": null, "value": null, "income_types": ["DIVIDENDS"], "other_income_spec": null, "amount_of_income": null, "transaction": null}
  ],
  "free_text": null,
  "uncertainties": [],
  "page_confidence": "high"
}
